casbin_async_sqlalchemy_adapter/__init__.py
casbin_async_sqlalchemy_adapter/adapter.py
casbin_async_sqlalchemy_adapter-1.12.0.data/data/README.md
casbin_async_sqlalchemy_adapter-1.12.0.dist-info/licenses/LICENSE
casbin_async_sqlalchemy_adapter-1.12.0.dist-info/METADATA
casbin_async_sqlalchemy_adapter-1.12.0.dist-info/WHEEL
casbin_async_sqlalchemy_adapter-1.12.0.dist-info/top_level.txt
casbin_async_sqlalchemy_adapter-1.12.0.dist-info/RECORD
