Metadata-Version: 2.4
Name: casbin_async_sqlalchemy_adapter
Version: 1.12.0
Summary: Asynchronous SQLAlchemy Adapter for PyCasbin
Home-page: https://github.com/officialpycasbin/async-sqlalchemy-adapter
Author: Casbin
Author-email: admin@casbin.org
License: Apache 2.0
Keywords: asynccasbin,SQLAlchemy,casbin-adapter,rbac,access control,abac,acl,permission
Classifier: Programming Language :: Python :: 3.9
Classifier: Programming Language :: Python :: 3.10
Classifier: Programming Language :: Python :: 3.11
Classifier: Programming Language :: Python :: 3.12
Classifier: License :: OSI Approved :: Apache Software License
Classifier: Operating System :: OS Independent
Requires-Python: >=3.7
License-File: LICENSE
Requires-Dist: SQLAlchemy>=1.4.0
Requires-Dist: pycasbin>=2.0.0
Dynamic: author
Dynamic: author-email
Dynamic: classifier
Dynamic: description
Dynamic: description-content-type
Dynamic: home-page
Dynamic: keywords
Dynamic: license
Dynamic: license-file
Dynamic: requires-dist
Dynamic: requires-python
Dynamic: summary
